flood_tool/__init__.py
flood_tool/analysis.py
flood_tool/geo.py
flood_tool/live.py
flood_tool/mapping.py
flood_tool/tool.py
msoiflood-1.0.dist-info/METADATA
msoiflood-1.0.dist-info/WHEEL
msoiflood-1.0.dist-info/top_level.txt
msoiflood-1.0.dist-info/RECORD
